textdirectory/__init__.py
textdirectory/cli.py
textdirectory/crudespellchecker.py
textdirectory/helpers.py
textdirectory/textdirectory.py
textdirectory/transformations.py
textdirectory/data/language_models/crudesc_lm_ame.gz.lm
textdirectory/data/language_models/crudesc_lm_amehistorical.gz.lm
textdirectory/data/language_models/crudesc_lm_en.gz.lm
textdirectory/data/stopwords/stopwords_en.txt
textdirectory/data/testdata/Text_A.txt
textdirectory/data/testdata/Text_B.txt
textdirectory/data/testdata/Text_C.txt
textdirectory/data/testdata/Text_D.txt
textdirectory/data/testdata/text_E.txt
textdirectory/data/testdata/level_2/Text_2_A.txt
textdirectory/data/testdata/level_2/Text_2_B.txt
textdirectory/data/testdata/level_2/Text_2_C.txt
textdirectory/data/testdata/level_2/Text_2_D.txt
textdirectory/data/testdata/level_2/Text_2_E.txt
textdirectory-0.3.3.dist-info/AUTHORS.rst
textdirectory-0.3.3.dist-info/LICENSE
textdirectory-0.3.3.dist-info/METADATA
textdirectory-0.3.3.dist-info/WHEEL
textdirectory-0.3.3.dist-info/dependency_links.txt
textdirectory-0.3.3.dist-info/entry_points.txt
textdirectory-0.3.3.dist-info/top_level.txt
textdirectory-0.3.3.dist-info/RECORD
