Metadata-Version: 2.1
Name: textdirectory
Version: 0.3.3
Summary: TextDirectory allows you to combine multiple text files into one. While doing this, filters and transformations can be applied.
Home-page: https://github.com/IngoKl/textdirectory
Author: Ingo Kleiber
Author-email: ingo@kleiber.me
License: MIT license
Keywords: textdirectory
Platform: UNKNOWN
Classifier: Development Status :: 2 - Pre-Alpha
Classifier: Intended Audience :: Developers
Classifier: License :: OSI Approved :: MIT License
Classifier: Natural Language :: English
Classifier: Programming Language :: Python :: 3.6
License-File: LICENSE
License-File: AUTHORS.rst
Requires-Dist: click
Requires-Dist: numpy
Requires-Dist: requests
Requires-Dist: beautifulsoup4
Requires-Dist: spacy
Requires-Dist: psutil
Requires-Dist: en-core-web-sm
Requires-Dist: twine
Requires-Dist: lxml
Requires-Dist: tqdm
